MANIFEST.in
setup.py
docx/__init__.py
docx/core.py
docx/dsl.py
docx/elements.py
docx/metadata.py
docx/utils.py
docx.egg-info/PKG-INFO
docx.egg-info/SOURCES.txt
docx.egg-info/dependency_links.txt
docx.egg-info/top_level.txt