Metadata-Version: 1.1
Name: docx
Version: 0.1.2
Summary: The docx module creates, reads and writes Microsoft Office Word 2007 docx files
Home-page: http://github.com/mikemaccana/python-docx
Author: Mike MacCana
Author-email: python.docx@librelist.com
License: UNKNOWN
Platform: UNKNOWN
Requires: lxml
Requires: python_dateutil
